ABDOELBALF/GG.wav
ABDOELBALF/__init__.py
ABDOELBALF/abdo.png
ABDOELBALF/main.py
ABDOELBALF-0.1.dist-info/METADATA
ABDOELBALF-0.1.dist-info/WHEEL
ABDOELBALF-0.1.dist-info/top_level.txt
ABDOELBALF-0.1.dist-info/RECORD
